Design.v
`timescale 1ns / 1ps
//////////////////////////////////////////////////////////////////////////////////
// Company: 
// Engineer: 
// 
// Create Date: 22.04.2026 10:25:36
// Design Name: 
// Module Name: Tff
// Project Name: 
// Target Devices: 
// Tool Versions: 
// Description: 
// 
// Dependencies: 
// 
// Revision:
// Revision 0.01 - File Created
// Additional Comments:
// 
//////////////////////////////////////////////////////////////////////////////////


module Tff(
   input T_i, 
   input clk_i, 
   input rst_i, 
   output reg Q_o, 
   output Qbar_o
);

assign Qbar_o = ~Q_o;

always@(posedge clk_i)
   if(rst_i)
      Q_o <= 1'b0;
   else if(T_i)
      Q_o <= ~Q_o;

endmodule

Testbench.v
`timescale 1ns / 1ps
//////////////////////////////////////////////////////////////////////////////////
// Company: 
// Engineer: 
// 
// Create Date: 22.04.2026 10:26:01
// Design Name: 
// Module Name: tb_Tff
// Project Name: 
// Target Devices: 
// Tool Versions: 
// Description: 
// 
// Dependencies: 
// 
// Revision:
// Revision 0.01 - File Created
// Additional Comments:
// 
//////////////////////////////////////////////////////////////////////////////////


module tb_Tff();
reg T_ti;
reg clk_ti;
reg rst_ti;
wire Q_to;
wire Qbar_to;

//net(s)
reg exp_Q;
reg exp_Qbar;
integer pass;
integer fail;
integer count;

//instantiation
Tff UUT(.T_i(T_ti), 
   .clk_i(clk_ti), 
   .rst_i(rst_ti), 
   .Q_o(Q_to), 
   .Qbar_o(Qbar_to));

//initialization
initial begin
pass = 0;
fail = 0;
count = 0;
exp_Q = 1'b0;
exp_Qbar = 1'b1;
end

//clock
initial begin
clk_ti = 1'b0;
forever
   #5 clk_ti = ~clk_ti;
end

//Reset
initial begin
rst_ti = 1'b1;
#7 rst_ti = 1'b0;
end

//feeding
initial begin
T_ti = 1'b0;
#12 T_ti = 1'b1;
#10 T_ti = 1'b0;
#10 T_ti = 1'b1;
repeat(10)
   #10 T_ti = $urandom_range(0, 1);
#5 $display("-----------");
$display("Total Ckecks: %d | Pass: %d, Fail: %d", count, pass, fail);
$display("-----------");
#5 $finish;
end

always@(posedge clk_ti)
   #1 checker;

//Self checker
task checker(); begin
   if(rst_ti) //Reset will initialize exp_Q
      exp_Q = 1'b0;
   else case(T_ti)
         1'b0: exp_Q = exp_Q;
         1'b1: exp_Q = ~exp_Q;
         default: exp_Q = exp_Q;
        endcase
   exp_Qbar = ~exp_Q;
if((exp_Q !== Q_to) || (exp_Qbar !== Qbar_to)) begin
   $display("Error | Time: %0t, Clock: %b, Reset: %b | T: %b | Q: %b, Q+: %b | Expected Q: %b, Q+: %b", $time, clk_ti, rst_ti, T_ti, Q_to, Qbar_to, exp_Q, exp_Qbar);
   fail = fail + 1;
end
else begin
   pass = pass + 1;
end
count = count + 1;
end
endtask

//capture
initial begin
$dumpfile("Tff.vcd");
$dumpvars(0, tb_Tff);
end

endmodule

Tff.vcd
$date
   Wed Apr 22 19:23:36 2026
$end

$version
  2025.2
  $dumpfile ("Tff.vcd") 
$end

$timescale
  1ps
$end

$scope module tb_Tff $end
$var reg 1 ! T_ti $end
$var reg 1 " clk_ti $end
$var reg 1 # rst_ti $end
$var wire 1 $ Q_to $end
$var wire 1 % Qbar_to $end
$var reg 1 & exp_Q $end
$var reg 1 ' exp_Qbar $end
$var integer 32 ( pass [31:0] $end
$var integer 32 ) fail [31:0] $end
$var integer 32 * count [31:0] $end
$scope module UUT $end
$var wire 1 + T_i $end
$var wire 1 , clk_i $end
$var wire 1 - rst_i $end
$var reg 1 . Q_o $end
$var wire 1 % Qbar_o $end
$upscope $end
$scope task checker $end
$upscope $end
$upscope $end
$enddefinitions $end

#0
$dumpvars
0!
0"
1#
x$
x%
0&
1'
b0 (
b0 )
b0 *
0+
0,
1-
x.
$end

#5000
1"
0$
1%
1,
0.

#6000
b1 (
b1 *

#7000
0#
0-

#10000
0"
0,

#12000
1!
1+

#15000
1"
1$
0%
1,
1.

#16000
1&
0'
b10 (
b10 *

#20000
0"
0,

#22000
0!
0+

#25000
1"
1,

#26000
b11 (
b11 *

#30000
0"
0,

#32000
1!
1+

#35000
1"
0$
1%
1,
0.

#36000
0&
1'
b100 (
b100 *

#40000
0"
0,

#45000
1"
1$
0%
1,
1.

#46000
1&
0'
b101 (
b101 *

#50000
0"
0,

#55000
1"
0$
1%
1,
0.

#56000
0&
1'
b110 (
b110 *

#60000
0"
0,

#62000
0!
0+

#65000
1"
1,

#66000
b111 (
b111 *

#70000
0"
0,

#75000
1"
1,

#76000
b1000 (
b1000 *

#80000
0"
0,

#82000
1!
1+

#85000
1"
1$
0%
1,
1.

#86000
1&
0'
b1001 (
b1001 *

#90000
0"
0,

#95000
1"
0$
1%
1,
0.

#96000
0&
1'
b1010 (
b1010 *

#100000
0"
0,

#105000
1"
1$
0%
1,
1.

#106000
1&
0'
b1011 (
b1011 *

#110000
0"
0,

#112000
0!
0+

#115000
1"
1,

#116000
b1100 (
b1100 *

#120000
0"
0,

#122000
1!
1+

#125000
1"
0$
1%
1,
0.

#126000
0&
1'
b1101 (
b1101 *

#130000
0"
0,

#135000
1"
1$
0%
1,
1.

#136000
1&
0'
b1110 (
b1110 *

